{
  "timestamp": "2026-07-24T18:01:48.327289Z",
  "pairs": [
    {
      "id": "XAUUSD",
      "symbol": "XAUUSD",
      "price": 4055.52795,
      "signal": null,
      "sl": null,
      "tp": null,
      "adx": 23.0,
      "rsi": 40.6,
      "atr": 3.13,
      "structure": "Neutre",
      "zone": "Discount",
      "bos": null,
      "choch": null,
      "reason": "Conditions non r\u00e9unies",
      "scoreTotal": 52,
      "quality": "FAIBLE",
      "dailyBias": "Neutre",
      "weeklyBias": "Neutre",
      "digits": 2,
      "scoreItems": [
        {
          "label": "BOS",
          "ok": false,
          "detail": "Dans range",
          "pts": 0,
          "max": 20,
          "cat": "SMC"
        },
        {
          "label": "CHoCH",
          "ok": false,
          "detail": "\u2014",
          "pts": 0,
          "max": 15,
          "cat": "SMC"
        },
        {
          "label": "Zone P/D",
          "ok": true,
          "detail": "Discount",
          "pts": 12,
          "max": 12,
          "cat": "SMC"
        },
        {
          "label": "Sweep Liq.",
          "ok": false,
          "detail": "\u2014",
          "pts": 0,
          "max": 20,
          "cat": "SMC"
        },
        {
          "label": "Order Block",
          "ok": false,
          "detail": "\u2014",
          "pts": 0,
          "max": 18,
          "cat": "SMC"
        },
        {
          "label": "FVG",
          "ok": false,
          "detail": "\u2014",
          "pts": 0,
          "max": 15,
          "cat": "SMC"
        },
        {
          "label": "RSI",
          "ok": true,
          "detail": "40.6",
          "pts": 5,
          "max": 5,
          "cat": "Indicateur"
        },
        {
          "label": "MACD",
          "ok": false,
          "detail": "Baissier",
          "pts": 0,
          "max": 5,
          "cat": "Indicateur"
        },
        {
          "label": "EMA Trend",
          "ok": false,
          "detail": "Baissier",
          "pts": 0,
          "max": 8,
          "cat": "Indicateur"
        },
        {
          "label": "Bollinger",
          "ok": false,
          "detail": "\u2014",
          "pts": 0,
          "max": 6,
          "cat": "Indicateur"
        },
        {
          "label": "Patterns",
          "ok": false,
          "detail": "\u2014",
          "pts": 0,
          "max": 6,
          "cat": "Pattern"
        },
        {
          "label": "OTE",
          "ok": false,
          "detail": "\u2014",
          "pts": 0,
          "max": 10,
          "cat": "SMC"
        },
        {
          "label": "Manipulation",
          "ok": true,
          "detail": "Aucune",
          "pts": 15,
          "max": 15,
          "cat": "Robustesse"
        },
        {
          "label": "Volume",
          "ok": false,
          "detail": "POC: 4055.53",
          "pts": 0,
          "max": 10,
          "cat": "Volume"
        },
        {
          "label": "Cascade TF",
          "ok": false,
          "detail": "30% align\u00e9",
          "pts": 0,
          "max": 15,
          "cat": "Confluence"
        },
        {
          "label": "Liquidit\u00e9",
          "ok": true,
          "detail": "N/A",
          "pts": 10,
          "max": 10,
          "cat": "March\u00e9"
        },
        {
          "label": "Multi-Ex",
          "ok": true,
          "detail": "Convergence 95%",
          "pts": 10,
          "max": 10,
          "cat": "Robustesse"
        }
      ],
      "patterns": [],
      "divergences": [],
      "ichimoku": {
        "tenkan": 4057.667645,
        "kijun": 4059.32879,
        "senkouA": 4058.4982175,
        "senkouB": 4056.029255
      },
      "manipulation": {
        "fakeBos": false,
        "inducement": null,
        "score": 100
      },
      "volumeProfile": {
        "profile": [
          {
            "price": 4047.4168941000003,
            "volume": 100
          },
          {
            "price": 4051.47242205,
            "volume": 110
          },
          {
            "price": 4055.52795,
            "volume": 120
          },
          {
            "price": 4059.5834779499996,
            "volume": 130
          },
          {
            "price": 4063.6390059,
            "volume": 140
          }
        ],
        "poc": 4055.52795,
        "delta": -9.414812275447254,
        "score": 48.11703754491055
      },
      "cascade": {
        "score": 30,
        "details": [
          {
            "label": "daily",
            "aligned": true
          },
          {
            "label": "weekly",
            "aligned": true
          }
        ]
      },
      "exchange": {
        "prices": [
          4055.52795,
          4055.933502795,
          4055.122397205
        ],
        "avg": 4055.52795,
        "dispersion": 0.81111,
        "score": 95.00000000000064
      },
      "scs": {
        "score": 29,
        "details": [
          {
            "label": "BOS strength",
            "value": "0",
            "pts": 0
          },
          {
            "label": "CHoCH force",
            "value": "0",
            "pts": 0
          },
          {
            "label": "OB quality",
            "value": "0",
            "pts": 0
          },
          {
            "label": "FVG quality",
            "value": "5",
            "pts": 5
          },
          {
            "label": "Multi-TF align\u00e9es",
            "value": "2 / 4",
            "pts": 6
          },
          {
            "label": "Bias Daily/Weekly",
            "value": "Neutre/Neutre",
            "pts": 12
          },
          {
            "label": "Killzone",
            "value": "active",
            "pts": 6
          }
        ]
      },
      "plan": null,
      "entryPrice": null,
      "slPrice": null,
      "tp1Price": null,
      "tp2Price": null,
      "tp3Price": null,
      "bePrice": null,
      "trailingStart": null,
      "zones": [
        {
          "kind": "RES",
          "dir": "bear",
          "label": "Resistance",
          "value": 4064.73,
          "pts": 2.9
        },
        {
          "kind": "SUP",
          "dir": "bull",
          "label": "Support",
          "value": 4051.7,
          "pts": -1.2
        },
        {
          "kind": "FVG",
          "dir": "bull",
          "label": "FVG",
          "value": 4058.22,
          "pts": 0.9
        }
      ],
      "resLevels": [
        4064.73,
        4063.17
      ],
      "supLevels": [
        4051.7,
        4053.26
      ],
      "bbMid": 4059.99,
      "ev": "0.60",
      "momentum": "Baissier",
      "cumDelta": 12.1,
      "emaTrend": "Baissier",
      "majorTrend": "Neutre",
      "macdHist": -0.7489,
      "finalProb": 0.55,
      "mcProb": 0.5,
      "mlProb": null,
      "confidenceDetails": "Zone P/D \u00b7 RSI \u00b7 Manipulation \u00b7 Liquidit\u00e9 \u00b7 Multi-Ex",
      "h1BiasText": "Neutre",
      "chochText": "Pas de CHoCH",
      "action": "Pas de signal",
      "inOTE": false,
      "fibo618": 4059.75,
      "candles": {}
    },
    {
      "id": "USDJPY",
      "symbol": "USDJPY",
      "price": 163.74072,
      "signal": null,
      "sl": null,
      "tp": null,
      "adx": 19.4,
      "rsi": 46.2,
      "atr": 0.034,
      "structure": "Neutre",
      "zone": "Discount",
      "bos": null,
      "choch": null,
      "reason": "Conditions non r\u00e9unies",
      "scoreTotal": 63,
      "quality": "ATTENDRE",
      "dailyBias": "Neutre",
      "weeklyBias": "Neutre",
      "digits": 3,
      "scoreItems": [
        {
          "label": "BOS",
          "ok": false,
          "detail": "Dans range",
          "pts": 0,
          "max": 20,
          "cat": "SMC"
        },
        {
          "label": "CHoCH",
          "ok": false,
          "detail": "\u2014",
          "pts": 0,
          "max": 15,
          "cat": "SMC"
        },
        {
          "label": "Zone P/D",
          "ok": true,
          "detail": "Discount",
          "pts": 12,
          "max": 12,
          "cat": "SMC"
        },
        {
          "label": "Sweep Liq.",
          "ok": false,
          "detail": "\u2014",
          "pts": 0,
          "max": 20,
          "cat": "SMC"
        },
        {
          "label": "Order Block",
          "ok": false,
          "detail": "\u2014",
          "pts": 0,
          "max": 18,
          "cat": "SMC"
        },
        {
          "label": "FVG",
          "ok": false,
          "detail": "\u2014",
          "pts": 0,
          "max": 15,
          "cat": "SMC"
        },
        {
          "label": "RSI",
          "ok": true,
          "detail": "46.2",
          "pts": 5,
          "max": 5,
          "cat": "Indicateur"
        },
        {
          "label": "MACD",
          "ok": true,
          "detail": "Haussier",
          "pts": 5,
          "max": 5,
          "cat": "Indicateur"
        },
        {
          "label": "EMA Trend",
          "ok": false,
          "detail": "Baissier",
          "pts": 0,
          "max": 8,
          "cat": "Indicateur"
        },
        {
          "label": "Bollinger",
          "ok": false,
          "detail": "\u2014",
          "pts": 0,
          "max": 6,
          "cat": "Indicateur"
        },
        {
          "label": "Patterns",
          "ok": true,
          "detail": "\u23fa \ud83d\udc3b",
          "pts": 6,
          "max": 6,
          "cat": "Pattern"
        },
        {
          "label": "OTE",
          "ok": false,
          "detail": "\u2014",
          "pts": 0,
          "max": 10,
          "cat": "SMC"
        },
        {
          "label": "Manipulation",
          "ok": true,
          "detail": "Aucune",
          "pts": 15,
          "max": 15,
          "cat": "Robustesse"
        },
        {
          "label": "Volume",
          "ok": false,
          "detail": "POC: 163.741",
          "pts": 0,
          "max": 10,
          "cat": "Volume"
        },
        {
          "label": "Cascade TF",
          "ok": false,
          "detail": "30% align\u00e9",
          "pts": 0,
          "max": 15,
          "cat": "Confluence"
        },
        {
          "label": "Liquidit\u00e9",
          "ok": true,
          "detail": "N/A",
          "pts": 10,
          "max": 10,
          "cat": "March\u00e9"
        },
        {
          "label": "Multi-Ex",
          "ok": true,
          "detail": "Convergence 95%",
          "pts": 10,
          "max": 10,
          "cat": "Robustesse"
        }
      ],
      "patterns": [
        {
          "type": "Doji",
          "icon": "\u23fa"
        },
        {
          "type": "Bearish Engulfing",
          "icon": "\ud83d\udc3b"
        }
      ],
      "divergences": [],
      "ichimoku": {
        "tenkan": 163.72484500000002,
        "kijun": 163.74738000000002,
        "senkouA": 163.73611250000002,
        "senkouB": 163.78844500000002
      },
      "manipulation": {
        "fakeBos": false,
        "inducement": null,
        "score": 100
      },
      "volumeProfile": {
        "profile": [
          {
            "price": 163.41323856,
            "volume": 100
          },
          {
            "price": 163.57697928000002,
            "volume": 110
          },
          {
            "price": 163.74072,
            "volume": 120
          },
          {
            "price": 163.90446072,
            "volume": 130
          },
          {
            "price": 164.06820144000002,
            "volume": 140
          }
        ],
        "poc": 163.74072,
        "delta": -3.8418636180877215,
        "score": 49.231627276382454
      },
      "cascade": {
        "score": 30,
        "details": [
          {
            "label": "daily",
            "aligned": true
          },
          {
            "label": "weekly",
            "aligned": true
          }
        ]
      },
      "exchange": {
        "prices": [
          163.74072,
          163.757094072,
          163.72434592800002
        ],
        "avg": 163.74072,
        "dispersion": 0.03275,
        "score": 95.00000000000283
      },
      "scs": {
        "score": 29,
        "details": [
          {
            "label": "BOS strength",
            "value": "0",
            "pts": 0
          },
          {
            "label": "CHoCH force",
            "value": "0",
            "pts": 0
          },
          {
            "label": "OB quality",
            "value": "0",
            "pts": 0
          },
          {
            "label": "FVG quality",
            "value": "5",
            "pts": 5
          },
          {
            "label": "Multi-TF align\u00e9es",
            "value": "2 / 4",
            "pts": 6
          },
          {
            "label": "Bias Daily/Weekly",
            "value": "Neutre/Neutre",
            "pts": 12
          },
          {
            "label": "Killzone",
            "value": "active",
            "pts": 6
          }
        ]
      },
      "plan": null,
      "entryPrice": null,
      "slPrice": null,
      "tp1Price": null,
      "tp2Price": null,
      "tp3Price": null,
      "bePrice": null,
      "trailingStart": null,
      "zones": [
        {
          "kind": "RES",
          "dir": "bear",
          "label": "Resistance",
          "value": 163.85,
          "pts": 3.2
        },
        {
          "kind": "SUP",
          "dir": "bull",
          "label": "Support",
          "value": 163.686,
          "pts": -1.6
        },
        {
          "kind": "FVG",
          "dir": "bull",
          "label": "FVG",
          "value": 163.768,
          "pts": 0.8
        }
      ],
      "resLevels": [
        163.85,
        163.833
      ],
      "supLevels": [
        163.686,
        163.703
      ],
      "bbMid": 163.746,
      "ev": "0.60",
      "momentum": "Neutre",
      "cumDelta": -0.089,
      "emaTrend": "Baissier",
      "majorTrend": "Neutre",
      "macdHist": 0.0025,
      "finalProb": 0.55,
      "mcProb": 0.5,
      "mlProb": null,
      "confidenceDetails": "Zone P/D \u00b7 RSI \u00b7 MACD \u00b7 Patterns \u00b7 Manipulation \u00b7 Liquidit\u00e9 \u00b7 Multi-Ex",
      "h1BiasText": "Neutre",
      "chochText": "Pas de CHoCH",
      "action": "Pas de signal",
      "inOTE": false,
      "fibo618": 163.788,
      "candles": {}
    },
    {
      "id": "USDCAD",
      "symbol": "USDCAD",
      "price": 1.40862,
      "signal": null,
      "sl": null,
      "tp": null,
      "adx": 28.0,
      "rsi": 58.5,
      "atr": 0.00035,
      "structure": "Neutre",
      "zone": "Premium",
      "bos": null,
      "choch": null,
      "reason": "Conditions non r\u00e9unies",
      "scoreTotal": 55,
      "quality": "ATTENDRE",
      "dailyBias": "Neutre",
      "weeklyBias": "Neutre",
      "digits": 5,
      "scoreItems": [
        {
          "label": "BOS",
          "ok": false,
          "detail": "Dans range",
          "pts": 0,
          "max": 20,
          "cat": "SMC"
        },
        {
          "label": "CHoCH",
          "ok": false,
          "detail": "\u2014",
          "pts": 0,
          "max": 15,
          "cat": "SMC"
        },
        {
          "label": "Zone P/D",
          "ok": false,
          "detail": "Premium",
          "pts": 0,
          "max": 12,
          "cat": "SMC"
        },
        {
          "label": "Sweep Liq.",
          "ok": false,
          "detail": "\u2014",
          "pts": 0,
          "max": 20,
          "cat": "SMC"
        },
        {
          "label": "Order Block",
          "ok": false,
          "detail": "\u2014",
          "pts": 0,
          "max": 18,
          "cat": "SMC"
        },
        {
          "label": "FVG",
          "ok": false,
          "detail": "\u2014",
          "pts": 0,
          "max": 15,
          "cat": "SMC"
        },
        {
          "label": "RSI",
          "ok": true,
          "detail": "58.5",
          "pts": 5,
          "max": 5,
          "cat": "Indicateur"
        },
        {
          "label": "MACD",
          "ok": true,
          "detail": "Haussier",
          "pts": 5,
          "max": 5,
          "cat": "Indicateur"
        },
        {
          "label": "EMA Trend",
          "ok": false,
          "detail": "Baissier",
          "pts": 0,
          "max": 8,
          "cat": "Indicateur"
        },
        {
          "label": "Bollinger",
          "ok": false,
          "detail": "\u2014",
          "pts": 0,
          "max": 6,
          "cat": "Indicateur"
        },
        {
          "label": "Patterns",
          "ok": false,
          "detail": "\u2014",
          "pts": 0,
          "max": 6,
          "cat": "Pattern"
        },
        {
          "label": "OTE",
          "ok": false,
          "detail": "\u2014",
          "pts": 0,
          "max": 10,
          "cat": "SMC"
        },
        {
          "label": "Manipulation",
          "ok": true,
          "detail": "Aucune",
          "pts": 15,
          "max": 15,
          "cat": "Robustesse"
        },
        {
          "label": "Volume",
          "ok": true,
          "detail": "POC: 1.40862",
          "pts": 10,
          "max": 10,
          "cat": "Volume"
        },
        {
          "label": "Cascade TF",
          "ok": false,
          "detail": "30% align\u00e9",
          "pts": 0,
          "max": 15,
          "cat": "Confluence"
        },
        {
          "label": "Liquidit\u00e9",
          "ok": true,
          "detail": "N/A",
          "pts": 10,
          "max": 10,
          "cat": "March\u00e9"
        },
        {
          "label": "Multi-Ex",
          "ok": true,
          "detail": "Convergence 95%",
          "pts": 10,
          "max": 10,
          "cat": "Robustesse"
        }
      ],
      "patterns": [],
      "divergences": [],
      "ichimoku": {
        "tenkan": 1.40815,
        "kijun": 1.408115,
        "senkouA": 1.4081325,
        "senkouB": 1.409405
      },
      "manipulation": {
        "fakeBos": false,
        "inducement": null,
        "score": 100
      },
      "volumeProfile": {
        "profile": [
          {
            "price": 1.40580276,
            "volume": 100
          },
          {
            "price": 1.40721138,
            "volume": 110
          },
          {
            "price": 1.40862,
            "volume": 120
          },
          {
            "price": 1.4100286199999998,
            "volume": 130
          },
          {
            "price": 1.41143724,
            "volume": 140
          }
        ],
        "poc": 1.40862,
        "delta": 8.535728964924289,
        "score": 51.70714579298486
      },
      "cascade": {
        "score": 30,
        "details": [
          {
            "label": "daily",
            "aligned": true
          },
          {
            "label": "weekly",
            "aligned": true
          }
        ]
      },
      "exchange": {
        "prices": [
          1.40862,
          1.408760862,
          1.408479138
        ],
        "avg": 1.40862,
        "dispersion": 0.00028,
        "score": 94.99999999999734
      },
      "scs": {
        "score": 29,
        "details": [
          {
            "label": "BOS strength",
            "value": "0",
            "pts": 0
          },
          {
            "label": "CHoCH force",
            "value": "0",
            "pts": 0
          },
          {
            "label": "OB quality",
            "value": "0",
            "pts": 0
          },
          {
            "label": "FVG quality",
            "value": "5",
            "pts": 5
          },
          {
            "label": "Multi-TF align\u00e9es",
            "value": "2 / 4",
            "pts": 6
          },
          {
            "label": "Bias Daily/Weekly",
            "value": "Neutre/Neutre",
            "pts": 12
          },
          {
            "label": "Killzone",
            "value": "active",
            "pts": 6
          }
        ]
      },
      "plan": null,
      "entryPrice": null,
      "slPrice": null,
      "tp1Price": null,
      "tp2Price": null,
      "tp3Price": null,
      "bePrice": null,
      "trailingStart": null,
      "zones": [
        {
          "kind": "RES",
          "dir": "bear",
          "label": "Resistance",
          "value": 1.40907,
          "pts": 1.3
        },
        {
          "kind": "SUP",
          "dir": "bull",
          "label": "Support",
          "value": 1.40731,
          "pts": -3.7
        },
        {
          "kind": "FVG",
          "dir": "bull",
          "label": "FVG",
          "value": 1.40819,
          "pts": -1.2
        }
      ],
      "resLevels": [
        1.40907,
        1.40889
      ],
      "supLevels": [
        1.40731,
        1.40749
      ],
      "bbMid": 1.40792,
      "ev": "0.50",
      "momentum": "Neutre",
      "cumDelta": -0.00163,
      "emaTrend": "Baissier",
      "majorTrend": "Neutre",
      "macdHist": 0.0002,
      "finalProb": 0.5,
      "mcProb": 0.5,
      "mlProb": null,
      "confidenceDetails": "RSI \u00b7 MACD \u00b7 Manipulation \u00b7 Volume \u00b7 Liquidit\u00e9 \u00b7 Multi-Ex",
      "h1BiasText": "Neutre",
      "chochText": "Pas de CHoCH",
      "action": "Pas de signal",
      "inOTE": true,
      "fibo618": 1.4084,
      "candles": {}
    }
  ]
}